col_spanish/__init__.py
col_spanish/col_spanish.py
col_spanish/encrypt.py
col_spanish-0.0.4.dist-info/LICENSE
col_spanish-0.0.4.dist-info/WHEEL
col_spanish-0.0.4.dist-info/METADATA
col_spanish-0.0.4.dist-info/RECORD
