Metadata-Version: 2.1
Name: col-spanish
Version: 0.0.4
Summary: Functions that help to work with text in spanish (Colombia)
Home-page: https://github.com/sergioasb8/col-spanish
License: MIT
Keywords: spanish,nlp,colombia,text-normalization
Author: Sergio Sosa Bautista
Author-email: sergioasb@gmail.com
Requires-Python: >=3,<4
Classifier: License :: OSI Approved :: MIT License
Classifier: Operating System :: OS Independent
Classifier: Programming Language :: Python
Classifier: Programming Language :: Python :: 3
Classifier: Programming Language :: Python :: 3.4
Classifier: Programming Language :: Python :: 3.5
Classifier: Programming Language :: Python :: 3.6
Classifier: Programming Language :: Python :: 3.7
Classifier: Programming Language :: Python :: 3.8
Classifier: Programming Language :: Python :: 3.9
Classifier: Programming Language :: Python :: 3.10
Classifier: Programming Language :: Python :: 3.11
Classifier: Programming Language :: Python :: 3
Project-URL: Repository, https://github.com/sergioasb8/col-spanish
